pitszi/__init__.py
pitszi/data_main.py
pitszi/inference_fluctuation_fitting.py
pitszi/inference_fluctuation_main.py
pitszi/inference_radial_fitting.py
pitszi/inference_radial_main.py
pitszi/model_library.py
pitszi/model_main.py
pitszi/model_mock.py
pitszi/model_sampling.py
pitszi/physics_main.py
pitszi/title.py
pitszi/utils.py
pitszi/utils_fitting.py
pitszi/utils_pk.py
pitszi/utils_plot.py
pitszi-0.3.0.dist-info/LICENSE
pitszi-0.3.0.dist-info/METADATA
pitszi-0.3.0.dist-info/WHEEL
pitszi-0.3.0.dist-info/top_level.txt
pitszi-0.3.0.dist-info/RECORD
