Metadata-Version: 2.2
Name: pitszi
Version: 0.3.0
Summary: Python code to model ICM pressure fluctuations, generate Monte Carlo Sunyaev-Zeldovich data, and fit the model to input data
Home-page: https://github.com/remi-adam/pitszi
Author: Remi Adam
Author-email: remi.adam@oca.eu
License: BSD
Classifier: Development Status :: 4 - Beta
Classifier: Intended Audience :: Science/Research
Classifier: Topic :: Scientific/Engineering :: Astronomy
Classifier: License :: OSI Approved :: BSD License
Classifier: Programming Language :: Python :: 3
License-File: LICENSE
Requires-Dist: numpy>=1.6
Requires-Dist: scipy
Requires-Dist: astropy>=1.2.1
Requires-Dist: matplotlib
Requires-Dist: emcee
Requires-Dist: corner
Requires-Dist: pandas
Requires-Dist: seaborn
Requires-Dist: dill
Requires-Dist: pathos
Requires-Dist: minot
Dynamic: author
Dynamic: author-email
Dynamic: classifier
Dynamic: description
Dynamic: description-content-type
Dynamic: home-page
Dynamic: license
Dynamic: requires-dist
Dynamic: summary
